docs2us_pdf_cli/__init__.py
docs2us_pdf_cli/main.py
docs2us_pdf_cli-1.0.0.dist-info/LICENSE
docs2us_pdf_cli-1.0.0.dist-info/METADATA
docs2us_pdf_cli-1.0.0.dist-info/WHEEL
docs2us_pdf_cli-1.0.0.dist-info/entry_points.txt
docs2us_pdf_cli-1.0.0.dist-info/RECORD
