Metadata-Version: 2.1
Name: docs2us-pdf-cli
Version: 1.0.0
Summary: A CLI tool for analyzing PDFs
License: MIT
Author: K Boehm
Author-email: kevin.boehm@orangeinfusion.com
Requires-Python: >=3.10,<4.0
Classifier: License :: OSI Approved :: MIT License
Classifier: Programming Language :: Python :: 3
Classifier: Programming Language :: Python :: 3.10
Classifier: Programming Language :: Python :: 3.11
Requires-Dist: click (>=8.1.7,<9.0.0)
Requires-Dist: pymupdf (>=1.24.0,<2.0.0)
